evative7_test_pkg/__init__.py
evative7_test_pkg-3.0.1.dist-info/METADATA
evative7_test_pkg-3.0.1.dist-info/WHEEL
evative7_test_pkg-3.0.1.dist-info/RECORD
