Metadata-Version: 2.4
Name: evative7_test_pkg
Version: 3.0.1
Project-URL: Homepage, https://github.com/EvATive7/hello_world
Author: EvATive7
Classifier: Operating System :: OS Independent
Classifier: Programming Language :: Python :: 3
Requires-Python: >=3.10
Provides-Extra: dev
Requires-Dist: editables; extra == 'dev'
Requires-Dist: hatch-vcs; extra == 'dev'
Requires-Dist: hatchling; extra == 'dev'
Requires-Dist: pytest; extra == 'dev'
Requires-Dist: ruff; extra == 'dev'
